retrieve_sentence_embeddings.py
retrieve_sentence_embeddings-0.1.0a0.dist-info/licenses/LICENSE
retrieve_sentence_embeddings-0.1.0a0.dist-info/METADATA
retrieve_sentence_embeddings-0.1.0a0.dist-info/WHEEL
retrieve_sentence_embeddings-0.1.0a0.dist-info/top_level.txt
retrieve_sentence_embeddings-0.1.0a0.dist-info/RECORD
