Metadata-Version: 2.4
Name: retrieve-sentence-embeddings
Version: 0.1.0a0
Summary: A simple function to retrieve sentence embeddings from an OpenAI Embeddings-compatible API.
Author-email: Jifeng Wu <jifengwu2k@gmail.com>
License-Expression: MIT
Project-URL: Homepage, https://github.com/jifengwu2k/retrieve-sentence-embeddings
Project-URL: Bug Tracker, https://github.com/jifengwu2k/retrieve-sentence-embeddings/issues
Classifier: Programming Language :: Python :: 2
Classifier: Programming Language :: Python :: 3
Classifier: Operating System :: OS Independent
Requires-Python: >=2
License-File: LICENSE
Requires-Dist: typing; python_version < "3.5"
Dynamic: license-file
